{"stats":{"minecraft:killed":{"minecraft:spider":5,"minecraft:skeleton":2,"minecraft:chicken":23,"minecraft:piglin_brute":3,"minecraft:magma_cube":16,"minecraft:piglin":2,"minecraft:pig":10,"minecraft:iron_golem":1,"minecraft:sheep":17,"minecraft:zombie":8,"minecraft:cow":7,"minecraft:blaze":8,"minecraft:drowned":1,"minecraft:wither_skeleton":2},"minecraft:broken":{"minecraft:stone_pickaxe":1,"minecraft:stone_axe":1,"minecraft:iron_pickaxe":1},"minecraft:mined":{"minecraft:spruce_planks":2,"minecraft:white_bed":3,"minecraft:granite":21,"minecraft:grass_block":22,"minecraft:cracked_polished_blackstone_bricks":9,"minecraft:gilded_blackstone":3,"minecraft:spawner":1,"minecraft:polished_blackstone_bricks":11,"minecraft:iron_ore":75,"minecraft:fire":16,"minecraft:deepslate_lapis_ore":10,"minecraft:blackstone":36,"minecraft:torch":8,"minecraft:poppy":1,"minecraft:chest":10,"minecraft:sugar_cane":4,"minecraft:oak_planks":13,"minecraft:wall_torch":1,"minecraft:pink_petals":8,"minecraft:warped_nylium":6,"minecraft:birch_log":34,"minecraft:grass":102,"minecraft:oak_log":98,"minecraft:dirt":20,"minecraft:netherrack":98,"minecraft:oak_leaves":25,"minecraft:deepslate":95,"minecraft:diamond_ore":9,"minecraft:tuff":21,"minecraft:deepslate_diamond_ore":16,"minecraft:spruce_leaves":4,"minecraft:large_fern":1,"minecraft:furnace":2,"minecraft:nether_sprouts":1,"minecraft:andesite":17,"minecraft:potatoes":1,"minecraft:deepslate_iron_ore":6,"minecraft:warped_stem":6,"minecraft:stone":105,"minecraft:basalt":89,"minecraft:dandelion":1,"minecraft:crafting_table":11,"minecraft:cornflower":1,"minecraft:tall_grass":26,"minecraft:deepslate_gold_ore":18,"minecraft:polished_blackstone_brick_stairs":2,"minecraft:diorite":47,"minecraft:birch_planks":5,"minecraft:purple_bed":1,"minecraft:spruce_log":6,"minecraft:birch_leaves":1,"minecraft:coal_ore":22,"minecraft:gravel":4,"minecraft:gold_ore":10},"minecraft:picked_up":{"minecraft:wooden_axe":1,"minecraft:birch_door":4,"minecraft:iron_chestplate":6,"minecraft:wheat":18,"minecraft:diamond_sword":8,"minecraft:potion":7,"minecraft:enchanted_book":4,"minecraft:gilded_blackstone":16,"minecraft:nether_brick":62,"minecraft:polished_blackstone_brick_stairs":1,"minecraft:string":118,"minecraft:iron_leggings":2,"minecraft:netherite_ingot":1,"minecraft:diamond_leggings":11,"minecraft:gold_nugget":14,"minecraft:cobbled_deepslate":203,"minecraft:bucket":1,"minecraft:spruce_planks":11,"minecraft:white_tulip":1,"minecraft:rose_bush":1,"minecraft:wooden_shovel":2,"minecraft:netherite_upgrade_smithing_template":4,"minecraft:iron_pickaxe":7,"minecraft:furnace":3,"minecraft:iron_boots":10,"minecraft:golden_helmet":2,"minecraft:stick":22,"minecraft:torch":12,"minecraft:porkchop":25,"minecraft:golden_axe":1,"minecraft:cherry_log":1,"minecraft:diorite":47,"minecraft:end_crystal":6,"minecraft:rabbit_foot":1,"minecraft:stone_sword":4,"minecraft:rotten_flesh":14,"minecraft:blaze_rod":24,"minecraft:obsidian":13,"minecraft:cobblestone":178,"minecraft:birch_log":49,"minecraft:pink_petals":106,"minecraft:feather":42,"minecraft:cooked_beef":10,"minecraft:magma_cream":16,"minecraft:andesite":17,"minecraft:tuff":21,"minecraft:wither_skeleton_skull":1,"minecraft:lapis_lazuli":112,"minecraft:dirt":132,"minecraft:bone":10,"minecraft:wheat_seeds":11,"minecraft:raw_gold":56,"minecraft:light_blue_dye":1,"minecraft:diamond_helmet":5,"minecraft:oak_planks":420,"minecraft:cooked_porkchop":38,"minecraft:grass_block":1,"minecraft:spectral_arrow":360,"minecraft:diamond":50,"minecraft:netherite_helmet":1,"minecraft:cracked_polished_blackstone_bricks":11,"minecraft:granite":21,"minecraft:emerald":18,"minecraft:oak_sapling":11,"minecraft:netherrack":120,"minecraft:fishing_rod":2,"minecraft:crafting_table":16,"minecraft:azure_bluet":1,"minecraft:chicken":23,"minecraft:wooden_pickaxe":4,"minecraft:gold_block":12,"minecraft:shield":1,"minecraft:cornflower":1,"minecraft:iron_axe":3,"minecraft:blackstone":158,"minecraft:beef":22,"minecraft:iron_nugget":24,"minecraft:poppy":3,"minecraft:light_gray_wool":1,"minecraft:sugar_cane":10,"minecraft:chest":11,"minecraft:egg":1,"minecraft:raw_iron":162,"minecraft:orange_dye":1,"minecraft:stone":6,"minecraft:fire_charge":16,"minecraft:polished_blackstone_bricks":28,"minecraft:prismarine_crystals":6,"minecraft:dark_oak_planks":2,"minecraft:arrow":16,"minecraft:diamond_chestplate":7,"minecraft:diamond_boots":5,"minecraft:totem_of_undying":55,"minecraft:gold_ingot":118,"minecraft:mutton":39,"minecraft:white_wool":15,"minecraft:basalt":100,"minecraft:golden_carrot":375,"minecraft:leather":82,"minecraft:filled_map":2,"minecraft:birch_planks":84,"minecraft:oak_log":125,"minecraft:ancient_debris":9,"minecraft:golden_boots":3,"minecraft:cooked_mutton":10,"minecraft:warped_stem":6,"minecraft:heart_of_the_sea":1,"minecraft:iron_ingot":26,"minecraft:stone_pickaxe":8,"minecraft:soul_sand":84,"minecraft:birch_boat":8,"minecraft:quartz":134,"minecraft:dandelion":10,"minecraft:lava_bucket":1,"minecraft:gravel":63,"minecraft:spruce_sapling":2,"minecraft:white_bed":7,"minecraft:spruce_log":6,"minecraft:crying_obsidian":82,"minecraft:purple_bed":2,"minecraft:stone_axe":8,"minecraft:iron_helmet":6,"minecraft:warped_roots":1,"minecraft:black_wool":2,"minecraft:coal":69,"minecraft:ender_pearl":27},"minecraft:killed_by":{"minecraft:player":6},"minecraft:custom":{"minecraft:interact_with_crafting_table":24,"minecraft:open_barrel":3,"minecraft:bell_ring":2,"minecraft:leave_game":23,"minecraft:time_since_death":5401,"minecraft:damage_resisted":189,"minecraft:sprint_one_cm":367062,"minecraft:damage_blocked_by_shield":60,"minecraft:drop":349,"minecraft:play_time":246092,"minecraft:deaths":14,"minecraft:jump":3131,"minecraft:walk_on_water_one_cm":16412,"minecraft:interact_with_furnace":16,"minecraft:sleep_in_bed":6,"minecraft:damage_dealt":13010,"minecraft:player_kills":6,"minecraft:crouch_one_cm":40241,"minecraft:mob_kills":105,"minecraft:climb_one_cm":3034,"minecraft:walk_one_cm":379820,"minecraft:sneak_time":12243,"minecraft:walk_under_water_one_cm":23328,"minecraft:boat_one_cm":82418,"minecraft:total_world_time":246092,"minecraft:time_since_rest":5426,"minecraft:damage_taken":7738,"minecraft:damage_absorbed":416,"minecraft:swim_one_cm":6570,"minecraft:fly_one_cm":758955,"minecraft:open_chest":30,"minecraft:fall_one_cm":108087},"minecraft:used":{"minecraft:ladder":1,"minecraft:chest":11,"minecraft:shield":3,"minecraft:rotten_flesh":1,"minecraft:mutton":5,"minecraft:obsidian":85,"minecraft:lava_bucket":19,"minecraft:villager_spawn_egg":3,"minecraft:grass_block":44,"minecraft:furnace":2,"minecraft:oak_sapling":2,"minecraft:egg":1,"minecraft:golden_boots":1,"minecraft:diamond_boots":1,"minecraft:birch_leaves":9,"minecraft:stone_pickaxe":273,"minecraft:oak_planks":452,"minecraft:blackstone":11,"minecraft:wooden_pickaxe":3,"minecraft:redstone_torch":1,"minecraft:golden_helmet":2,"minecraft:diamond_sword":204,"minecraft:bone_meal":4,"minecraft:stone_sword":1,"minecraft:spruce_planks":25,"minecraft:cooked_chicken":4,"minecraft:netherrack":165,"minecraft:torch":15,"minecraft:dirt":134,"minecraft:diamond_helmet":1,"minecraft:granite":21,"minecraft:dark_oak_planks":2,"minecraft:iron_axe":37,"minecraft:polished_blackstone_brick_stairs":1,"minecraft:iron_boots":2,"minecraft:totem_of_undying":3,"minecraft:light_gray_wool":1,"minecraft:diamond_chestplate":1,"minecraft:basalt":4,"minecraft:golden_carrot":20,"minecraft:cooked_beef":1,"minecraft:cobbled_deepslate":9,"minecraft:cherry_log":1,"minecraft:enchanted_golden_apple":2,"minecraft:iron_leggings":1,"minecraft:cooked_mutton":8,"minecraft:water_bucket":5,"minecraft:cobblestone_stairs":1,"minecraft:birch_planks":70,"minecraft:birch_boat":10,"minecraft:polished_blackstone_bricks":19,"minecraft:warped_roots":1,"minecraft:gilded_blackstone":3,"minecraft:crafting_table":12,"minecraft:white_bed":8,"minecraft:warped_planks":24,"minecraft:oak_log":3,"minecraft:cracked_polished_blackstone_bricks":7,"minecraft:iron_pickaxe":458,"minecraft:stone_axe":176,"minecraft:pink_petals":64,"minecraft:cobblestone":16,"minecraft:potion":1,"minecraft:end_crystal":100,"minecraft:purple_bed":2,"minecraft:cooked_porkchop":3,"minecraft:porkchop":1,"minecraft:bucket":24,"minecraft:diamond_leggings":1},"minecraft:crafted":{"minecraft:oak_planks":396,"minecraft:purple_bed":1,"minecraft:cooked_chicken":4,"minecraft:birch_boat":4,"minecraft:cooked_mutton":3,"minecraft:warped_planks":24,"minecraft:iron_boots":1,"minecraft:chest":1,"minecraft:cooked_porkchop":11,"minecraft:crafting_table":2,"minecraft:spruce_planks":24,"minecraft:wooden_pickaxe":2,"minecraft:birch_planks":120,"minecraft:iron_chestplate":1,"minecraft:purple_dye":2,"minecraft:shield":1,"minecraft:stick":8,"minecraft:furnace":1,"minecraft:stone_pickaxe":1,"minecraft:golden_helmet":1,"minecraft:red_dye":1,"minecraft:bucket":1,"minecraft:stone_axe":1,"minecraft:bread":6,"minecraft:air":0,"minecraft:blue_dye":1,"minecraft:white_bed":3,"minecraft:torch":4},"minecraft:dropped":{"minecraft:orange_dye":1,"minecraft:oak_log":512,"minecraft:spore_blossom":1,"minecraft:ender_pearl":1,"minecraft:glass_bottle":1,"minecraft:diamond":2,"minecraft:orange_tulip":1,"minecraft:netherite_upgrade_smithing_template":2,"minecraft:emerald":6,"minecraft:cracked_polished_blackstone_bricks":4,"minecraft:dirt":9,"minecraft:cornflower":1,"minecraft:mutton":7,"minecraft:polished_blackstone_bricks":1,"minecraft:iron_pickaxe":2,"minecraft:fishing_rod":2,"minecraft:white_wool":6,"minecraft:gold_ingot":182,"minecraft:bone":6,"minecraft:gravel":8,"minecraft:white_tulip":1,"minecraft:stone_axe":5,"minecraft:blackstone":1,"minecraft:ancient_debris":3,"minecraft:cobbled_deepslate":22,"minecraft:obsidian":2,"minecraft:rotten_flesh":9,"minecraft:enchanted_golden_apple":65,"minecraft:azure_bluet":2,"minecraft:white_bed":1,"minecraft:rabbit_foot":1,"minecraft:poppy":3,"minecraft:basalt":64,"minecraft:quartz":34,"minecraft:torchflower":1,"minecraft:golden_boots":1,"minecraft:iron_ingot":4,"minecraft:wheat_seeds":9,"minecraft:diamond_leggings":6,"minecraft:netherite_helmet":1,"minecraft:feather":1,"minecraft:iron_helmet":2,"minecraft:cobblestone":22,"minecraft:purple_dye":1,"minecraft:grass_block":1,"minecraft:coal":1,"minecraft:oxeye_daisy":1,"minecraft:golden_carrot":102,"minecraft:torch":1,"minecraft:rose_bush":1,"minecraft:diamond_helmet":5,"minecraft:potion":2,"minecraft:wither_rose":1,"minecraft:iron_axe":1,"minecraft:string":4,"minecraft:pink_petals":262,"minecraft:dandelion":11,"minecraft:pink_tulip":1,"minecraft:stone_sword":1,"minecraft:tuff":21,"minecraft:wither_skeleton_skull":3,"minecraft:iron_boots":3,"minecraft:totem_of_undying":56,"minecraft:lily_of_the_valley":1,"minecraft:filled_map":2,"minecraft:diamond_sword":2,"minecraft:light_blue_dye":1,"minecraft:stone":6,"minecraft:allium":1,"minecraft:diamond_chestplate":7,"minecraft:iron_chestplate":1,"minecraft:andesite":17,"minecraft:oak_sapling":9,"minecraft:wooden_shovel":2,"minecraft:diamond_boots":5,"minecraft:birch_boat":1,"minecraft:blue_orchid":1,"minecraft:stone_pickaxe":1,"minecraft:wooden_pickaxe":3,"minecraft:red_tulip":1}},"DataVersion":3463}